[
    {
        "id": "gsec10yr",
        "name": "ICICI Prudential Nifty 10yr Benchmark G-Sec ETF",
        "ticker": "GSEC10YEAR",
        "nseSymbol": "GSEC10IETF",
        "exchange": "NSE",
        "category": "Debt - G-Sec",
        "color": "#FFA726",
        "index": {
            "name": "Nifty 10yr Benchmark G-Sec Index",
            "launched": "October 2021",
            "methodology": "Constant Maturity Government Securities",
            "rebalance": "Monthly (roll to on-the-run 10yr bond)",
            "companies": 1,
            "description": "Government of India Securities (G-Secs) represent pure sovereign credit — zero default risk. The 10-year benchmark G-Sec is RBI's primary policy transmission instrument. In June 2024, India's 10-year G-Sec inclusion in JP Morgan GBI-EM (Global Bond Index) triggered ~$25 billion passive foreign inflows, creating structural demand. Investors benefit from dual returns: (1) coupon income (7-8% annualized), (2) capital appreciation when RBI cuts rates (inverse relationship: rate ↓ → price ↑). Ideal for retirees seeking stable income, long-term wealth preservation, and tax efficiency (indexation benefit on long-term gains). G-Secs suitable for laddering strategy where 5-year, 10-year and 20-year bonds provide staggered maturity. RBI Open Market Operations use benchmark G-Secs as primary instrument, making them most liquid debt securities globally. During Fed rate hike cycles, G-Secs suffer from capital losses (rate ↑ → price ↓), but during easing cycles (post-2025 expected), substantial capital gains likely."
        },
        "indexKey": "nifty-10yr-benchmark-g-sec-index"
    },
    {
        "id": "niftygilt5yr",
        "name": "Nippon India ETF Nifty 5yr Benchmark G-Sec",
        "ticker": "GILT5YBEES",
        "nseSymbol": "GILT5BETA",
        "exchange": "NSE",
        "category": "Debt - G-Sec",
        "color": "#FFCA28",
        "index": {
            "name": "Nifty 5yr Benchmark G-Sec Index",
            "launched": "December 2021",
            "methodology": "Constant Maturity Government Securities",
            "rebalance": "Monthly",
            "companies": 1,
            "description": "Tracks the on-the-run 5-year Government of India Security. Shorter duration than the 10yr ETF — less interest rate sensitivity. Suitable for investors wanting sovereign safety with moderate duration. Yield slightly below 10yr providing the normal upward-sloping yield curve exposure."
        },
        "indexKey": "nifty-5yr-benchmark-g-sec-index"
    },
    {
        "id": "ltgiltbees",
        "name": "Nippon India ETF Nifty 8-13 yr G-Sec Long Term Gilt",
        "ticker": "LTGILTBEES",
        "nseSymbol": "LTGILTBEES",
        "exchange": "NSE",
        "category": "Debt - G-Sec",
        "color": "#1565C0",
        "index": {
            "name": "NIFTY 8-13 yr G-Sec Index",
            "launched": "",
            "methodology": "Free-Float Market Cap",
            "rebalance": "Semi-Annual",
            "companies": 0,
            "description": "Nippon India ETF Nifty 8-13 yr G-Sec Long Term Gilt tracks the NIFTY 8-13 yr G-Sec Index index."
        },
        "indexKey": "nifty-8-13-yr-g-sec-index"
    },
    {
        "id": "gilt5ybees",
        "name": "NIPPON INDIA ETF NIFTY 5 YR BENCHMARK GSEC",
        "ticker": "GILT5YBEES",
        "nseSymbol": "GILT5YBEES",
        "exchange": "NSE",
        "category": "Debt - G-Sec",
        "color": "#1565C0",
        "index": {
            "name": "Nifty 5 yr Benchmark G-Sec Index",
            "launched": "",
            "methodology": "Free-Float Market Cap",
            "rebalance": "Semi-Annual",
            "companies": 0,
            "description": "NIPPON INDIA ETF NIFTY 5 YR BENCHMARK GSEC tracks the Nifty 5 yr Benchmark G-Sec Index index."
        },
        "indexKey": "nifty-5-yr-benchmark-g-sec-index"
    },
    {
        "id": "setf10gilt",
        "name": "SBI Mutual Fund - SBI-ETF 10 YEAR GILT ",
        "ticker": "SETF10GILT",
        "nseSymbol": "SETF10GILT",
        "exchange": "NSE",
        "category": "Debt - G-Sec",
        "color": "#1565C0",
        "index": {
            "name": "Nifty 10 yr Benchmark G-Sec Index",
            "launched": "",
            "methodology": "Free-Float Market Cap",
            "rebalance": "Semi-Annual",
            "companies": 0,
            "description": "SBI Mutual Fund - SBI-ETF 10 YEAR GILT  tracks the Nifty 10 yr Benchmark G-Sec Index index."
        },
        "indexKey": "nifty-10-yr-benchmark-g-sec-index"
    },
    {
        "id": "ltgiltcase",
        "name": "Zerodha Fund House - Zerodha Nifty 8-13 Yr G-Sec ETF",
        "ticker": "LTGILTCASE",
        "nseSymbol": "LTGILTCASE",
        "exchange": "NSE",
        "category": "Debt - G-Sec",
        "color": "#1565C0",
        "index": {
            "name": "Nifty 8-13 Yr G-Sec Index",
            "launched": "",
            "methodology": "Free-Float Market Cap",
            "rebalance": "Semi-Annual",
            "companies": 0,
            "description": "Zerodha Fund House - Zerodha Nifty 8-13 Yr G-Sec ETF tracks the Nifty 8-13 Yr G-Sec Index index."
        },
        "indexKey": "nifty-8-13-yr-g-sec-index"
    },
    {
        "id": "licnetfgsc",
        "name": "LIC MF - LIC MF G-sec LT ETF - GO",
        "ticker": "LICNETFGSC",
        "nseSymbol": "LICNETFGSC",
        "exchange": "NSE",
        "category": "Debt - G-Sec",
        "color": "#1565C0",
        "index": {
            "name": "GSEC10 NSE Index",
            "launched": "",
            "methodology": "Free-Float Market Cap",
            "rebalance": "Semi-Annual",
            "companies": 0,
            "description": "LIC MF - LIC MF G-sec LT ETF - GO tracks the GSEC10 NSE Index index."
        },
        "indexKey": "gsec10-nse-index"
    },
    {
        "id": "mogsec",
        "name": "Motilal Oswal Mutual Fund - Motilal Oswal 5 Year G Sec ETF - Growth",
        "ticker": "MOGSEC",
        "nseSymbol": "MOGSEC",
        "exchange": "NSE",
        "category": "Debt - G-Sec",
        "color": "#1565C0",
        "index": {
            "name": "Nifty 5 yr Benchmark G-Sec Index",
            "launched": "",
            "methodology": "Free-Float Market Cap",
            "rebalance": "Semi-Annual",
            "companies": 0,
            "description": "Motilal Oswal Mutual Fund - Motilal Oswal 5 Year G Sec ETF - Growth tracks the Nifty 5 yr Benchmark G-Sec Index index."
        },
        "indexKey": "nifty-5-yr-benchmark-g-sec-index"
    },
    {
        "id": "gsec5ietf",
        "name": "ICICI Prudential Nifty 5 Yr Benchmark G-SEC ETF",
        "ticker": "GSEC5IETF",
        "nseSymbol": "GSEC5IETF",
        "exchange": "NSE",
        "category": "Debt - G-Sec",
        "color": "#1565C0",
        "index": {
            "name": "Nifty 5 yr Benchmark G-Sec Index",
            "launched": "",
            "methodology": "Free-Float Market Cap",
            "rebalance": "Semi-Annual",
            "companies": 0,
            "description": "ICICI Prudential Nifty 5 Yr Benchmark G-SEC ETF tracks the Nifty 5 yr Benchmark G-Sec Index index."
        },
        "indexKey": "nifty-5-yr-benchmark-g-sec-index"
    },
    {
        "id": "gilt10beta",
        "name": "UTI Mutual Fund - UTI Nifty 10 yr Benchmark G-Sec ETF",
        "ticker": "GILT10BETA",
        "nseSymbol": "GILT10BETA",
        "exchange": "NSE",
        "category": "Debt - G-Sec",
        "color": "#1565C0",
        "index": {
            "name": "UTI Nifty 10 yr Benchmark G-Sec ETF",
            "launched": "",
            "methodology": "Free-Float Market Cap",
            "rebalance": "Semi-Annual",
            "companies": 0,
            "description": "UTI Mutual Fund - UTI Nifty 10 yr Benchmark G-Sec ETF tracks the UTI Nifty 10 yr Benchmark G-Sec ETF index."
        },
        "indexKey": "uti-nifty-10-yr-benchmark-g-sec-etf"
    },
    {
        "id": "abgsec",
        "name": "AdityaBirlaSunLifeMF-Aditya Birla Sun Life CRISIL Broad Based Gilt ETF",
        "ticker": "ABGSEC",
        "nseSymbol": "ABGSEC",
        "exchange": "NSE",
        "category": "Debt - G-Sec",
        "color": "#1565C0",
        "index": {
            "name": "Aditya Birla Sun Life CRISIL Broad Based Gilt ETF",
            "launched": "",
            "methodology": "Free-Float Market Cap",
            "rebalance": "Semi-Annual",
            "companies": 0,
            "description": "AdityaBirlaSunLifeMF-Aditya Birla Sun Life CRISIL Broad Based Gilt ETF tracks the Aditya Birla Sun Life CRISIL Broad Based Gilt ETF index."
        },
        "indexKey": "aditya-birla-sun-life-crisil-broad-based-gilt-etf"
    },
    {
        "id": "gsec10year",
        "name": "Mirae Asset Mutual Fund - Mirae Asset Nifty 8-13 yr G-Sec ETF",
        "ticker": "GSEC10YEAR",
        "nseSymbol": "GSEC10YEAR",
        "exchange": "NSE",
        "category": "Debt - G-Sec",
        "color": "#1565C0",
        "index": {
            "name": "Mirae Asset Nifty 8-13 yr G-Sec ETF",
            "launched": "",
            "methodology": "Free-Float Market Cap",
            "rebalance": "Semi-Annual",
            "companies": 0,
            "description": "Mirae Asset Mutual Fund - Mirae Asset Nifty 8-13 yr G-Sec ETF tracks the Mirae Asset Nifty 8-13 yr G-Sec ETF index."
        },
        "indexKey": "mirae-asset-nifty-8-13-yr-g-sec-etf"
    },
    {
        "id": "gsec10absl",
        "name": "AdityaBirlaSunLifeMF - Aditya Birla Sun Life CRISIL 10 Year Gilt ETF",
        "ticker": "GSEC10ABSL",
        "nseSymbol": "GSEC10ABSL",
        "exchange": "NSE",
        "category": "Debt - G-Sec",
        "color": "#1565C0",
        "index": {
            "name": "CRISIL 10 Year Gilt ETF",
            "launched": "",
            "methodology": "Free-Float Market Cap",
            "rebalance": "Semi-Annual",
            "companies": 0,
            "description": "AdityaBirlaSunLifeMF - Aditya Birla Sun Life CRISIL 10 Year Gilt ETF tracks the CRISIL 10 Year Gilt ETF index."
        },
        "indexKey": "crisil-10-year-gilt-etf"
    }
]