[
    {
        "id": "niftyrealty",
        "name": "Kotak Nifty Realty ETF",
        "ticker": "KOTAKREALTY",
        "nseSymbol": "MOREALTY",
        "exchange": "NSE",
        "category": "Sectoral - Realty",
        "color": "#8D6E63",
        "index": {
            "name": "Nifty Realty Index",
            "launched": "June 2007",
            "methodology": "Free-Float Market Cap",
            "rebalance": "Semi-Annual",
            "companies": 10,
            "description": "Nifty Realty tracks 10 listed developers commanding ~30% of organized real estate supply. Structural opportunity: India faces 18.78M unit shortage (vs 2M annual supply), suggesting 9-10 years of runaway growth. Three growth engines: (1) Residential — rise in per-capita income enabling home ownership (₹50 Lakh+ property prices from upper-middle-class expansion); (2) Office space — corporate capex for India offices generating 50M sq ft annually, with IT/ITeS tenants premium-paying ₹80-120/sqft vs traditional ₹40-60; (3) Malls/Retail — premiumisation of retail consumption driving mall footfall increase 5% annually. Margin profiles: residential pre-sales generate 25-30% EBITDA margins; commercial real estate 40-50% margins (yield: 7-9% rental yield); mall operations 60%+ margins. Asset-light models gain: DLF's Cyber City REIT (₹30K Cr valuation separate from residential DLF) provides recurring cash flows. Leverage risk: high debt-to-equity in sector (2-3x) creates negative NPV during downturns. Currency tailwind: NRI remittances (when rupee weakens, NRI realizations surge) drive 20% of luxury segment purchases. Regulatory benefit: RERA act ensured transparency, MahaRERA prosecutions deterred fraudsters, strengthening organized sector vs unorganized."
        },
        "indexKey": "nifty-realty-index"
    },
    {
        "id": "growwrlty",
        "name": "Groww Mutual Fund - Groww Nifty Realty ETF",
        "ticker": "GROWWRLTY",
        "nseSymbol": "GROWWRLTY",
        "exchange": "NSE",
        "category": "Sectoral - Realty",
        "color": "#880E4F",
        "index": {
            "name": "Index",
            "launched": "",
            "methodology": "Free-Float Market Cap",
            "rebalance": "Semi-Annual",
            "companies": 0,
            "description": "Groww Mutual Fund - Groww Nifty Realty ETF tracks the Index index."
        },
        "indexKey": "index"
    }
]